{"cameraMode":{"drawMode":0,"name":"Shaded","section":"Shading Mode"},"sceneLighting":false,"audioPlay":false,"sceneViewState":{"m_AlwaysRefresh":false,"showFog":false,"showSkybox":false,"showFlares":false,"showImageEffects":false,"showParticleSystems":false,"showVisualEffectGraphs":true,"m_FxEnabled":true},"in2DMode":false,"pivot":{"x":-0.462186336517334,"y":2.3440465927124025,"z":-0.38172054290771487},"rotation":{"x":0.05903162434697151,"y":0.9385679364204407,"z":-0.2725429832935333,"w":0.2032899111509323},"size":15.351144790649414,"orthographic":false}